Nanylibrary/Cliob.py
Nanylibrary/Nany.py
Nanylibrary/Ny_Wb.py
Nanylibrary/__init__.py
Nanylibrary/encryption.py
Nanylibrary-4.2.6.dist-info/LICENCE
Nanylibrary-4.2.6.dist-info/METADATA
Nanylibrary-4.2.6.dist-info/WHEEL
Nanylibrary-4.2.6.dist-info/top_level.txt
Nanylibrary-4.2.6.dist-info/RECORD
