Metadata-Version: 2.1
Name: Nanylibrary
Version: 4.2.6
Summary: library robot Rubika
Home-page: https://github.com/Nanymous/Nany_library.git
Author: Mohammad _GeNeRal_
Author-email: nanylibrary@gmail.com
License: MIT
Keywords: rubika,bot,robot,library,rubikalib,rubikalib.ml,rubikalib.ir,rubika.ir,Nanylibrary,nanylibrary,Nany,nany,Rubika,Python
Classifier: Development Status :: 3 - Alpha
Classifier: Intended Audience :: Developers
Classifier: Topic :: Software Development :: Build Tools
Classifier: License :: OSI Approved :: MIT License
Classifier: Programming Language :: Python :: Implementation :: PyPy
Classifier: Programming Language :: Python :: 3
Classifier: Programming Language :: Python :: 3.4
Classifier: Programming Language :: Python :: 3.5
Classifier: Programming Language :: Python :: 3.6
Classifier: Programming Language :: Python :: 3.7
Classifier: Programming Language :: Python :: 3.8
Classifier: Programming Language :: Python :: 3.9
License-File: LICENCE
